py_attio/__init__.py
py_attio/client.py
py_attio/utils.py
py_attio-0.7.0.dist-info/licenses/LICENSE
py_attio-0.7.0.dist-info/METADATA
py_attio-0.7.0.dist-info/WHEEL
py_attio-0.7.0.dist-info/top_level.txt
py_attio-0.7.0.dist-info/RECORD
