Metadata-Version: 2.4
Name: py-attio
Version: 0.7.0
Summary: A lightweight Python wrapper for the Attio API.
Author-email: Benjamin Hawn <ben@benjaminhawn.com>
Requires-Python: >=3.8
License-File: LICENSE
Requires-Dist: requests
Dynamic: license-file
